learning_to_rank/RankNet.py
learning_to_rank/__init__.py
learning_to_rank/lambdaRank.py
learning_to_rank/listwise.py
learning_to_rank/pairwise.py
learning_to_rank/poinstwise.py
learning_to_rank/utils.py
learning_to_rank-0.0.3.dist-info/LICENSE.txt
learning_to_rank-0.0.3.dist-info/METADATA
learning_to_rank-0.0.3.dist-info/WHEEL
learning_to_rank-0.0.3.dist-info/top_level.txt
learning_to_rank-0.0.3.dist-info/RECORD
