Metadata-Version: 2.1
Name: learning-to-rank
Version: 0.0.3
Summary: A small package for learning to rank
Home-page: https://github.com/guankaisi/learning_to_rank
Author: guankaisi
Author-email: guankaisi@ruc.edu.cn
Classifier: Programming Language :: Python :: 3
Classifier: License :: OSI Approved :: MIT License
Classifier: Operating System :: OS Independent
Requires-Python: >=3.6
License-File: LICENSE.txt
